[
    {
      "id": 1,
      "cover_img": "https://images.unsplash.com/photo-1581328011707-04dd5eaeae24?crop=entropy&cs=tinysrgb&fit=max&fm=jpg&ixid=MnwzNjUyOXwwfDF8c2VhcmNofDF8fHVuaXZlcnNlfGVufDB8fHx8MTYxNzI3MjI5OA&ixlib=rb-1.2.1&q=80&w=1080",
      "author_name": "Alice Johnson",
      "author_img": "https://images.unsplash.com/photo-1551836022-da7003d88c24?crop=entropy&cs=tinysrgb&fit=max&fm=jpg&ixid=MnwzNjUyOXwwfDF8c2VhcmNofDJ8fHBlcnNvbnxlbnwwfHx8fDE2MTcyNzIyOTg&ixlib=rb-1.2.1&q=80&w=1080",
      "post_title": "Exploring the Wonders of the Universe",
      "reading_time": 10,
      "hashtags": ["science", "space", "astronomy"]
    },
    {
      "id": 2,
      "cover_img": "https://images.pexels.com/photos/4244466/pexels-photo-4244466.jpeg?auto=compress&cs=tinysrgb&dpr=2&h=650&w=940",
      "author_name": "Bob Smith",
      "author_img": "https://images.pexels.com/photos/220453/pexels-photo-220453.jpeg?auto=compress&cs=tinysrgb&dpr=2&h=650&w=940",
      "post_title": "The Art of Minimalist Living",
      "reading_time": 8,
      "hashtags": ["lifestyle", "minimalism", "design"]
    },
    {
      "id": 3,
      "cover_img": "https://cdn.pixabay.com/photo/2016/11/29/03/40/meditation-1866942_1280.jpg",
      "author_name": "Carol Davis",
      "author_img": "https://cdn.pixabay.com/photo/2015/09/03/11/09/reading-918588_1280.jpg",
      "post_title": "A Guide to Mindful Meditation",
      "reading_time": 12,
      "hashtags": ["wellness", "meditation", "mindfulness"]
    },
    {
      "id": 4,
      "cover_img": "https://images.unsplash.com/photo-1516685018646-5499d0a1a6ff?crop=entropy&cs=tinysrgb&fit=max&fm=jpg&ixid=MnwzNjUyOXwwfDF8c2VhcmNofDF8fGNvb2tpbmclMjBhcnR8ZW58MHx8fHwxNjE3MjcyMzE0&ixlib=rb-1.2.1&q=80&w=1080",
      "author_name": "David Lee",
      "author_img": "https://images.unsplash.com/photo-1544006659-f0b21884ce1d?crop=entropy&cs=tinysrgb&fit=max&fm=jpg&ixid=MnwzNjUyOXwwfDF8c2VhcmNofDIzfHxwZXJzb258ZW58MHx8fHwxNjE3MjcyMzE0&ixlib=rb-1.2.1&q=80&w=1080",
      "post_title": "Mastering the Art of Cooking",
      "reading_time": 15,
      "hashtags": ["food", "cooking", "recipes"]
    },
    {
      "id": 5,
      "cover_img": "https://images.pexels.com/photos/3756158/pexels-photo-3756158.jpeg?auto=compress&cs=tinysrgb&dpr=2&h=650&w=940",
      "author_name": "Emma Brown",
      "author_img": "https://images.pexels.com/photos/4060146/pexels-photo-4060146.jpeg?auto=compress&cs=tinysrgb&dpr=2&h=650&w=940",
      "post_title": "Traveling the World on a Budget",
      "reading_time": 9,
      "hashtags": ["travel", "budget", "adventure"]
    }
  ]
  